dynamicpy/__init__.py
dynamicpy/dependencies.py
dynamicpy/errors.py
dynamicpy/loader.py
dynamicpy/model.py
dynamicpy/utils.py
dynamicpy/widgets.py
dynamicpy-1.3.1.dist-info/LICENCE
dynamicpy-1.3.1.dist-info/METADATA
dynamicpy-1.3.1.dist-info/WHEEL
dynamicpy-1.3.1.dist-info/RECORD
