Metadata-Version: 2.1
Name: dynamicpy
Version: 1.3.1
Summary: A python module for dynamically interacting with objects to improve expandability.
Home-page: https://github.com/NimajnebEC/dynamicpy
License: MIT
Author: NimajnebEC
Author-email: nimajnebec@users.noreply.github.com
Requires-Python: >=3.8,<4.0
Classifier: License :: OSI Approved :: MIT License
Classifier: Programming Language :: Python :: 3
Classifier: Programming Language :: Python :: 3.8
Classifier: Programming Language :: Python :: 3.9
Classifier: Programming Language :: Python :: 3.10
Classifier: Programming Language :: Python :: 3.11
Classifier: Programming Language :: Python :: 3.12
Requires-Dist: typeguard (>=4.0.0,<5.0.0)
Project-URL: Repository, https://github.com/NimajnebEC/dynamicpy
